hebill_html/README.MD
hebill_html/__init__.py
hebill_html/constants.py
hebill_html/core.py
hebill_html/tpl_style.py
hebill_html/components/__init__.py
hebill_html/components/alert/__init__.py
hebill_html/components/alert/color.py
hebill_html/components/alert/core.py
hebill_html/components/html/__init__.py
hebill_html/components/html/core.py
hebill_html/components/html/body/__init__.py
hebill_html/components/html/body/core.py
hebill_html/components/html/head/__init__.py
hebill_html/components/html/head/core.py
hebill_html/components/html/head/title/__init__.py
hebill_html/components/html/head/title/core.py
hebill_html/components/html/libraries/__init__.py
hebill_html/components/html/libraries/libraries.py
hebill_html/components/table/__init__.py
hebill_html/components/table/color.py
hebill_html/components/table/core.py
hebill_html/components/table/tbody/__init__.py
hebill_html/components/table/tbody/core.py
hebill_html/components/table/tbody/tr/__init__.py
hebill_html/components/table/tbody/tr/core.py
hebill_html/components/table/tbody/tr/td/__init__.py
hebill_html/components/table/tbody/tr/td/core.py
hebill_html/components/table/thead/__init__.py
hebill_html/components/table/thead/core.py
hebill_html/components/table/thead/tr/__init__.py
hebill_html/components/table/thead/tr/core.py
hebill_html/components/table/thead/tr/th/__init__.py
hebill_html/components/table/thead/tr/th/core.py
hebill_html/nodes/__init__.py
hebill_html/nodes/code/__init__.py
hebill_html/nodes/code/core.py
hebill_html/nodes/comment/__init__.py
hebill_html/nodes/comment/core.py
hebill_html/nodes/content/__init__.py
hebill_html/nodes/content/core.py
hebill_html/nodes/group/__init__.py
hebill_html/nodes/group/core.py
hebill_html/nodes/group/create/__init__.py
hebill_html/nodes/group/create/core.py
hebill_html/nodes/group/create/components/__init__.py
hebill_html/nodes/group/create/components/core.py
hebill_html/nodes/group/create/nodes/__init__.py
hebill_html/nodes/group/create/nodes/core.py
hebill_html-1.0.1.dist-info/METADATA
hebill_html-1.0.1.dist-info/WHEEL
hebill_html-1.0.1.dist-info/top_level.txt
hebill_html-1.0.1.dist-info/RECORD
